{
  "sourceDataInfo": {
    "newsID": "LC_M03_194780",
    "newsCategory": "생활&문화",
    "newsSubcategory": "책",
    "newsTitle": "[무엇부터 읽을까] 추리소설 제대로 읽으려면…",
    "newsSubTitle": "",
    "newsContent": "추리소설의 계보를 찾아올라 가노라면 필연적으로 에드거 앨런 포(1809~49)의 대표작 『모르그가의 살인사건』(1841)과 『도둑맞은 편지』(1845)를 만나게 된다.\n포가 창조한 천재탐정 오귀스트 뒤팽은 『모르그가의 살인사건』에서는 세계 최초의 밀실사건을 해결하고, 『도둑맞은 편지』에서는 경찰이 찾지 못한 숨겨진 편지를 손쉽게 찾아내 독자들을 감탄시킨다.\n특히 후자에서 포는 벌써 탐정과 범인의 유사성을 지적하는 놀랄 만한 혜안을 보여주고 있는데, 이 두 작품은 추리소설의 원조로서 우선 읽어야만 한다.\n포의 전통을 이어받아 뛰어난 추리소설을 써낸 작가는 영국인 의사 코넌 도일(1859~1930)이다.\n포를 모방해 불멸의 탐정 셜록 홈스와 그의 친구 겸 조수인 왓슨을 창조한 도일의 단편집 『셜록 홈스의 모험』(1892)과 장편소설 『바스커빌 가의 사냥개』(1902)는 오늘날 추리소설의 고전으로 필독서가 되었다.\n홈스의 탐정 사무실 주소인 런던의 베이커스가에는 지금도 홈스를 실제인물로 착각한 어린이들의 편지가 끊임없이 날아들어 아예 답장을 써주는 사람이 근무하고 있을 정도다.\n프랑스 최고의 추리작가는 단연 『괴도 루팽』 시리즈를 쓴 모리스 르블랑(1864년생)이다.\n홈스가 영국인들의 자랑이자 우상이었다면, 르블랑이 창조한 아르센 루팽은 제도권 수사기관을 조롱하는 천재 신사도둑으로서 프랑스 국민의 열렬한 환영을 받았다.\n루팽 시리즈 중 가장 널리 알려진 것은 『기암성』(1909)이다.\n독일의 추리작가 에리히 케스트너(1899~1974)의 『에밀과 탐정들』(1928)도 추리문학의 필독서다.\n이 소설이 성공한 이유 중 하나는, 에밀을 비롯한 소년소녀 탐정들의 시각으로 어른 세계의 범죄를 바라보고 비판했다는 데 있다.\n추리소설 독자라면 물론 영국작가 애거사 크리스티(1890~1976)의 대표작 『애크로이드 살인사건』(1926), 『오리엔트 특급살인』(1934),『나일강의 죽음』(1937), 『그리고 아무도 없었다』(원제 Ten Little Indians,1939)도 읽어야만 한다.\n미국인들이 좋아하는 『몰타의 매』(1930)의 작가 대시엘 해밋(1894~1961)은 실제 샌프란시스코 사립탐정이었던 자신의 경험을 살려, 냉혹한 터프가이 탐정이 등장하는 하드보일드 탐정소설 장르를 개척했으며, 『기나긴 이별』(원제 Big Sleep,1939)의 작가 레이먼드 챈들러(1888~1959) 역시 고독하고 냉정한 탐정 필립 말로를 창조했다.\n또 캘리포니아주 변호사 스탠리 얼 가드너(1889~1970)는 폭력 대신 오직 법만을 이용해 사건을 해결하는 유능한 변호사 페리 메이슨을 내세운 『명탐정 페리 메이슨』(탐구당) 시리즈를 썼다.\n포스트모던 추리소설 시대로 접어들면서, 최근에는 셜록 홈스 식의 이성적.연역적 추리나 터프가이 식의 폭력적 해결에 대한 불신과 패러디가 등장하기 시작했다.\n예컨대 호르헤 루이스 보르헤스의 중편 '죽음과 콤파스'(『바벨의 도서관』.『허구들』)나, 블라디미르 나보코프의 『세바스천 나이트의 참 인생』(청하), 또는 움베트로 에코의 『장미의 이름』(열린 책들) 같은 것들은 모두 이성적 추리만으로는 풀어지지 않는 오늘날의 복합적인 현실을 잘 묘사하고 있는 순수문학 추리소설들로서, 재미와 유익을 동시에 얻으며 읽을 수 있다.\n요즘의 미국 베스트셀러들 역시 대부분 추리소설의 기법을 차용하고 있다.\n예컨대 스티븐 킹의 『제럴드의 게임』(열음사)이나 『돌로레스 클레이본』(열음사), 또는 토머스 해리스의 『양들의 침묵』(창해)은 심리 추리소설이며, 존 그리샴의 『회사』나 『의뢰인』, 또는 톰 클랜시의 『붉은 폭풍』(잎새)이나 『붉은 10월호』는 스릴러 추리소설이다.\n이런 것들은 비록 대중소설로 분류되고 있기는 하지만, 문학성과 독창성도 꽤 인정받고 있는 새로운 형태의 추리소설들이다.",
    "partNum": "P1",
    "useType": 0,
    "processType": "D",
    "processPattern": "11",
    "processLevel": "하",
    "sentenceCount": 19,
    "sentenceInfo": [
      {
        "sentenceNo": 1,
        "sentenceContent": "추리소설의 계보를 찾아올라 가노라면 필연적으로 에드거 앨런 포(1809~49)의 대표작 『모르그가의 살인사건』(1841)과 『도둑맞은 편지』(1845)를 만나게 된다.",
        "sentenceSize": 93
      },
      {
        "sentenceNo": 2,
        "sentenceContent": "포가 창조한 천재탐정 오귀스트 뒤팽은 『모르그가의 살인사건』에서는 세계 최초의 밀실사건을 해결하고, 『도둑맞은 편지』에서는 경찰이 찾지 못한 숨겨진 편지를 손쉽게 찾아내 독자들을 감탄시킨다.",
        "sentenceSize": 106
      },
      {
        "sentenceNo": 3,
        "sentenceContent": "특히 후자에서 포는 벌써 탐정과 범인의 유사성을 지적하는 놀랄 만한 혜안을 보여주고 있는데, 이 두 작품은 추리소설의 원조로서 우선 읽어야만 한다.",
        "sentenceSize": 82
      },
      {
        "sentenceNo": 4,
        "sentenceContent": "포의 전통을 이어받아 뛰어난 추리소설을 써낸 작가는 영국인 의사 코넌 도일(1859~1930)이다.",
        "sentenceSize": 55
      },
      {
        "sentenceNo": 5,
        "sentenceContent": "포를 모방해 불멸의 탐정 셜록 홈스와 그의 친구 겸 조수인 왓슨을 창조한 도일의 단편집 『셜록 홈스의 모험』(1892)과 장편소설 『바스커빌 가의 사냥개』(1902)는 오늘날 추리소설의 고전으로 필독서가 되었다.",
        "sentenceSize": 118
      },
      {
        "sentenceNo": 6,
        "sentenceContent": "홈스의 탐정 사무실 주소인 런던의 베이커스가에는 지금도 홈스를 실제인물로 착각한 어린이들의 편지가 끊임없이 날아들어 아예 답장을 써주는 사람이 근무하고 있을 정도다.",
        "sentenceSize": 92
      },
      {
        "sentenceNo": 7,
        "sentenceContent": "프랑스 최고의 추리작가는 단연 『괴도 루팽』 시리즈를 쓴 모리스 르블랑(1864년생)이다.",
        "sentenceSize": 50
      },
      {
        "sentenceNo": 8,
        "sentenceContent": "홈스가 영국인들의 자랑이자 우상이었다면, 르블랑이 창조한 아르센 루팽은 제도권 수사기관을 조롱하는 천재 신사도둑으로서 프랑스 국민의 열렬한 환영을 받았다.",
        "sentenceSize": 86
      },
      {
        "sentenceNo": 9,
        "sentenceContent": "루팽 시리즈 중 가장 널리 알려진 것은 『기암성』(1909)이다.",
        "sentenceSize": 36
      },
      {
        "sentenceNo": 10,
        "sentenceContent": "독일의 추리작가 에리히 케스트너(1899~1974)의 『에밀과 탐정들』(1928)도 추리문학의 필독서다.",
        "sentenceSize": 58
      },
      {
        "sentenceNo": 11,
        "sentenceContent": "이 소설이 성공한 이유 중 하나는, 에밀을 비롯한 소년소녀 탐정들의 시각으로 어른 세계의 범죄를 바라보고 비판했다는 데 있다.",
        "sentenceSize": 70
      },
      {
        "sentenceNo": 12,
        "sentenceContent": "추리소설 독자라면 물론 영국작가 애거사 크리스티(1890~1976)의 대표작 『애크로이드 살인사건』(1926), 『오리엔트 특급살인』(1934),『나일강의 죽음』(1937), 『그리고 아무도 없었다』(원제 Ten Little Indians,1939)도 읽어야만 한다.",
        "sentenceSize": 149
      },
      {
        "sentenceNo": 13,
        "sentenceContent": "미국인들이 좋아하는 『몰타의 매』(1930)의 작가 대시엘 해밋(1894~1961)은 실제 샌프란시스코 사립탐정이었던 자신의 경험을 살려, 냉혹한 터프가이 탐정이 등장하는 하드보일드 탐정소설 장르를 개척했으며, 『기나긴 이별』(원제 Big Sleep,1939)의 작가 레이먼드 챈들러(1888~1959) 역시 고독하고 냉정한 탐정 필립 말로를 창조했다.",
        "sentenceSize": 197
      },
      {
        "sentenceNo": 14,
        "sentenceContent": "또 캘리포니아주 변호사 스탠리 얼 가드너(1889~1970)는 폭력 대신 오직 법만을 이용해 사건을 해결하는 유능한 변호사 페리 메이슨을 내세운 『명탐정 페리 메이슨』(탐구당) 시리즈를 썼다.",
        "sentenceSize": 107
      },
      {
        "sentenceNo": 15,
        "sentenceContent": "포스트모던 추리소설 시대로 접어들면서, 최근에는 셜록 홈스 식의 이성적.연역적 추리나 터프가이 식의 폭력적 해결에 대한 불신과 패러디가 등장하기 시작했다.",
        "sentenceSize": 86
      },
      {
        "sentenceNo": 16,
        "sentenceContent": "예컨대 호르헤 루이스 보르헤스의 중편 '죽음과 콤파스'(『바벨의 도서관』.『허구들』)나, 블라디미르 나보코프의 『세바스천 나이트의 참 인생』(청하), 또는 움베트로 에코의 『장미의 이름』(열린 책들) 같은 것들은 모두 이성적 추리만으로는 풀어지지 않는 오늘날의 복합적인 현실을 잘 묘사하고 있는 순수문학 추리소설들로서, 재미와 유익을 동시에 얻으며 읽을 수 있다.",
        "sentenceSize": 203
      },
      {
        "sentenceNo": 17,
        "sentenceContent": "요즘의 미국 베스트셀러들 역시 대부분 추리소설의 기법을 차용하고 있다.",
        "sentenceSize": 39
      },
      {
        "sentenceNo": 18,
        "sentenceContent": "예컨대 스티븐 킹의 『제럴드의 게임』(열음사)이나 『돌로레스 클레이본』(열음사), 또는 토머스 해리스의 『양들의 침묵』(창해)은 심리 추리소설이며, 존 그리샴의 『회사』나 『의뢰인』, 또는 톰 클랜시의 『붉은 폭풍』(잎새)이나 『붉은 10월호』는 스릴러 추리소설이다.",
        "sentenceSize": 149
      },
      {
        "sentenceNo": 19,
        "sentenceContent": "이런 것들은 비록 대중소설로 분류되고 있기는 하지만, 문학성과 독창성도 꽤 인정받고 있는 새로운 형태의 추리소설들이다.",
        "sentenceSize": 66
      }
    ]
  },
  "labeledDataInfo": {
    "newTitle": "추리소설의 진가를 알기 위한 'A부터 Z까지'··· 어떤 책들이 있을까?",
    "clickbaitClass": 0,
    "referSentenceInfo": [
      {
        "sentenceNo": 1,
        "referSentenceyn": "N"
      },
      {
        "sentenceNo": 2,
        "referSentenceyn": "N"
      },
      {
        "sentenceNo": 3,
        "referSentenceyn": "Y"
      },
      {
        "sentenceNo": 4,
        "referSentenceyn": "N"
      },
      {
        "sentenceNo": 5,
        "referSentenceyn": "N"
      },
      {
        "sentenceNo": 6,
        "referSentenceyn": "N"
      },
      {
        "sentenceNo": 7,
        "referSentenceyn": "N"
      },
      {
        "sentenceNo": 8,
        "referSentenceyn": "N"
      },
      {
        "sentenceNo": 9,
        "referSentenceyn": "N"
      },
      {
        "sentenceNo": 10,
        "referSentenceyn": "N"
      },
      {
        "sentenceNo": 11,
        "referSentenceyn": "N"
      },
      {
        "sentenceNo": 12,
        "referSentenceyn": "N"
      },
      {
        "sentenceNo": 13,
        "referSentenceyn": "N"
      },
      {
        "sentenceNo": 14,
        "referSentenceyn": "N"
      },
      {
        "sentenceNo": 15,
        "referSentenceyn": "N"
      },
      {
        "sentenceNo": 16,
        "referSentenceyn": "N"
      },
      {
        "sentenceNo": 17,
        "referSentenceyn": "N"
      },
      {
        "sentenceNo": 18,
        "referSentenceyn": "N"
      },
      {
        "sentenceNo": 19,
        "referSentenceyn": "Y"
      }
    ]
  }
}