{
  "sourceDataInfo": {
    "newsID": "LC_M03_195830",
    "newsCategory": "생활&문화",
    "newsSubcategory": "건강정보",
    "newsTitle": "메르스 포털, 환자 현황· 메르스 격리 병원 등 실시간 확인…종합적 창구 역할",
    "newsSubTitle": "",
    "newsContent": "'메르스 포털' 메르스 포털, 환자발생 현황부터 신고면회 등 기능까지...\\\"확산 방지 위해 병문안 자제\\\" 정부가 중동호흡기증후군(메르스·MERS)관련 정보를 실시간으로 전달하는 메르스 포털(www.mers.go.kr)을 개시했다.\n10일 중앙메르스관리대책본부는 \\\"메르스 정보를 살필 수 있는 메르스 포털 공식 사이트를 오픈해 정식 서비스를 시작했다\\\"라고 밝혔다.\n메르스 포털에는 환자 발생 의료기관, 환자발생 현황일반인 자가격리대상자, 여행자, 의료인 등 대상자별 유의사항 등이 기재되어 있다.\n또 메르스 응급의료기관 등 선별진료소 등 의료기관 찾기, 신고면회 등의 기능을 갖춰 메르스에 대한 종합적인 창구역할을 하게 될 전망이다.\n이날 보건복지부 관계자는 메르스 포털을 소개하며 “메르스 포털은 DUR시스템을 통해 중앙메르스관리대책본부에서 제공한 명단을 토대로 메르스 관련 일상접촉자 또는 격리대상자 정보를 한방진료 분야를 제외한 전체 의료기관에 실시간으로 제공하겠다”라고 설명했다.\n앞서, 정부는 메르스 확산에 따른 국민적 불안을 해소하기 위해 대한의사협회가 중동호흡기증후군(메르스) 관련 자가격리 및 지역사회 확산 방지 권고안을 발표했다.\n자가격리 권고안은 자가격리 대상자, 부양자·가족과 밀접 접촉자를 대상으로 한 예방조치의 일환으로, 실제 생활에서 실천할 수 있는 세부 행동요령을 정리했다.\n자가격리 대상자를 위한 예방조치로서 ▶자택에 있기 ▶자택 내 사람들과 떨어져 있기 ▶마스크를 사용하기 ▶손을 철저히 씻기 ▶생활용품 공동사용을 피하기 ▶증상 지속적으로 감시하기 등 7가지 행동요령 등이 마련돼 있다.\n부양자와 가족 및 밀접 접촉자를 위한 예방조치로는 ▶치료 등에 대한 설명과 지시를 잘 이해하고 환자·감시대상자 돕기 ▶환자를 도와줄 수 있는 사람만 집안에서 함께 생활하기 ▶공용으로 사용되는 장소는 에어컨, 열린 창문 등과 같이 환기가 잘되는지 확인하기 ▶환자·감시대상자의 혈액, 체액 또는 땀, 침 등과 같은 분비물을 만지거나 접촉해야 할 때 일회용 마스크, 가운과 장갑을 착용하기 ▶세탁을 철저히 하기 ▶사용한 모든 장갑, 가운, 마스크, 오염된 물건은 비닐봉지가 씌워진 통에 넣고 버리기 등의 행동요령이 만들어졌다.\n메르스 포털 소식에 들은 네티즌들은 \\\"메르스 포털, 진작에 이랬으면\\\" \\\"메르스 포털, 유용할까?\\\" \\\"메르스 포털, 매일 가서 확인해야겠네\\\" 등의 반응을 보였다. '메르스 포털' 온라인 중앙일보 [사진 중앙포토] '메르스 포털'",
    "partNum": "P1",
    "useType": 0,
    "processType": "D",
    "processPattern": "11",
    "processLevel": "하",
    "sentenceCount": 10,
    "sentenceInfo": [
      {
        "sentenceNo": 1,
        "sentenceContent": "'메르스 포털' 메르스 포털, 환자발생 현황부터 신고면회 등 기능까지...\\\"확산 방지 위해 병문안 자제\\\" 정부가 중동호흡기증후군(메르스·MERS)관련 정보를 실시간으로 전달하는 메르스 포털(www.mers.go.kr)을 개시했다.",
        "sentenceSize": 130
      },
      {
        "sentenceNo": 2,
        "sentenceContent": "10일 중앙메르스관리대책본부는 \\\"메르스 정보를 살필 수 있는 메르스 포털 공식 사이트를 오픈해 정식 서비스를 시작했다\\\"라고 밝혔다.",
        "sentenceSize": 75
      },
      {
        "sentenceNo": 3,
        "sentenceContent": "메르스 포털에는 환자 발생 의료기관, 환자발생 현황일반인 자가격리대상자, 여행자, 의료인 등 대상자별 유의사항 등이 기재되어 있다.",
        "sentenceSize": 73
      },
      {
        "sentenceNo": 4,
        "sentenceContent": "또 메르스 응급의료기관 등 선별진료소 등 의료기관 찾기, 신고면회 등의 기능을 갖춰 메르스에 대한 종합적인 창구역할을 하게 될 전망이다.",
        "sentenceSize": 76
      },
      {
        "sentenceNo": 5,
        "sentenceContent": "이날 보건복지부 관계자는 메르스 포털을 소개하며 “메르스 포털은 DUR시스템을 통해 중앙메르스관리대책본부에서 제공한 명단을 토대로 메르스 관련 일상접촉자 또는 격리대상자 정보를 한방진료 분야를 제외한 전체 의료기관에 실시간으로 제공하겠다”라고 설명했다.",
        "sentenceSize": 141
      },
      {
        "sentenceNo": 6,
        "sentenceContent": "앞서, 정부는 메르스 확산에 따른 국민적 불안을 해소하기 위해 대한의사협회가 중동호흡기증후군(메르스) 관련 자가격리 및 지역사회 확산 방지 권고안을 발표했다.",
        "sentenceSize": 88
      },
      {
        "sentenceNo": 7,
        "sentenceContent": "자가격리 권고안은 자가격리 대상자, 부양자·가족과 밀접 접촉자를 대상으로 한 예방조치의 일환으로, 실제 생활에서 실천할 수 있는 세부 행동요령을 정리했다.",
        "sentenceSize": 86
      },
      {
        "sentenceNo": 8,
        "sentenceContent": "자가격리 대상자를 위한 예방조치로서 ▶자택에 있기 ▶자택 내 사람들과 떨어져 있기 ▶마스크를 사용하기 ▶손을 철저히 씻기 ▶생활용품 공동사용을 피하기 ▶증상 지속적으로 감시하기 등 7가지 행동요령 등이 마련돼 있다.",
        "sentenceSize": 120
      },
      {
        "sentenceNo": 9,
        "sentenceContent": "부양자와 가족 및 밀접 접촉자를 위한 예방조치로는 ▶치료 등에 대한 설명과 지시를 잘 이해하고 환자·감시대상자 돕기 ▶환자를 도와줄 수 있는 사람만 집안에서 함께 생활하기 ▶공용으로 사용되는 장소는 에어컨, 열린 창문 등과 같이 환기가 잘되는지 확인하기 ▶환자·감시대상자의 혈액, 체액 또는 땀, 침 등과 같은 분비물을 만지거나 접촉해야 할 때 일회용 마스크, 가운과 장갑을 착용하기 ▶세탁을 철저히 하기 ▶사용한 모든 장갑, 가운, 마스크, 오염된 물건은 비닐봉지가 씌워진 통에 넣고 버리기 등의 행동요령이 만들어졌다.",
        "sentenceSize": 291
      },
      {
        "sentenceNo": 10,
        "sentenceContent": "메르스 포털 소식에 들은 네티즌들은 \\\"메르스 포털, 진작에 이랬으면\\\" \\\"메르스 포털, 유용할까?\\\" \\\"메르스 포털, 매일 가서 확인해야겠네\\\" 등의 반응을 보였다. '메르스 포털' 온라인 중앙일보 [사진 중앙포토] '메르스 포털'",
        "sentenceSize": 132
      }
    ]
  },
  "labeledDataInfo": {
    "newTitle": "메르스 포털, 중동호흡기증후군 관련 정보 실시간 전달… 어디까지 알려주나? ",
    "clickbaitClass": 0,
    "referSentenceInfo": [
      {
        "sentenceNo": 1,
        "referSentenceyn": "Y"
      },
      {
        "sentenceNo": 2,
        "referSentenceyn": "N"
      },
      {
        "sentenceNo": 3,
        "referSentenceyn": "N"
      },
      {
        "sentenceNo": 4,
        "referSentenceyn": "N"
      },
      {
        "sentenceNo": 5,
        "referSentenceyn": "N"
      },
      {
        "sentenceNo": 6,
        "referSentenceyn": "N"
      },
      {
        "sentenceNo": 7,
        "referSentenceyn": "N"
      },
      {
        "sentenceNo": 8,
        "referSentenceyn": "N"
      },
      {
        "sentenceNo": 9,
        "referSentenceyn": "N"
      },
      {
        "sentenceNo": 10,
        "referSentenceyn": "N"
      }
    ]
  }
}